aoa_pytorch/__init__.py
aoa_pytorch/aoa_pytorch.py
aoa_pytorch-0.0.2.dist-info/LICENSE
aoa_pytorch-0.0.2.dist-info/METADATA
aoa_pytorch-0.0.2.dist-info/WHEEL
aoa_pytorch-0.0.2.dist-info/top_level.txt
aoa_pytorch-0.0.2.dist-info/RECORD
